kosmos_client/__init__.py
kosmos_client/kosmos.py
kosmos_client/pytest_kosmos.py
kosmos_client-0.9.3.dist-info/LICENSE
kosmos_client-0.9.3.dist-info/METADATA
kosmos_client-0.9.3.dist-info/WHEEL
kosmos_client-0.9.3.dist-info/top_level.txt
kosmos_client-0.9.3.dist-info/RECORD
