Metadata-Version: 2.1
Name: kosmos-client
Version: 0.9.3
Summary: Client to connect to the KosmoS Platform
Home-page: https://kosmos-lab.de/python-client/
Author: Jan Janssen
Author-email: Jan.Janssen@dfki.de
License: MIT
Classifier: Programming Language :: Python :: 3
Classifier: License :: OSI Approved :: MIT License
Classifier: Operating System :: OS Independent
Requires-Python: >=3.6
License-File: LICENSE
Requires-Dist: websocket-client
Requires-Dist: requests
Requires-Dist: dataclasses-json
Requires-Dist: aioify
